README.rst
setup.cfg
setup.py
wolfe/__init__.py
wolfe/api.py
wolfe/wolfe.py
wolfe.egg-info/PKG-INFO
wolfe.egg-info/SOURCES.txt
wolfe.egg-info/dependency_links.txt
wolfe.egg-info/entry_points.txt
wolfe.egg-info/requires.txt
wolfe.egg-info/top_level.txt