Metadata-Version: 1.0
Name: wolfe
Version: 0.0.8
Summary: i am winston wolfe, i solve problems
Home-page: https://github.com/h4ck3rk3y/wolfe
Author: Gyanendra Mishra
Author-email: anomaly.the@gmail.com
License: MIT
Keywords: wolfe,bugs,errrors,stackoverflow,cli,google
Platform: UNKNOWN
